.git/FETCH_HEAD
.git/HEAD
.git/config
.git/description
.git/hooks/applypatch-msg.sample
.git/hooks/commit-msg.sample
.git/hooks/fsmonitor-watchman.sample
.git/hooks/post-update.sample
.git/hooks/pre-applypatch.sample
.git/hooks/pre-commit.sample
.git/hooks/pre-merge-commit.sample
.git/hooks/pre-push.sample
.git/hooks/pre-rebase.sample
.git/hooks/pre-receive.sample
.git/hooks/prepare-commit-msg.sample
.git/hooks/push-to-checkout.sample
.git/hooks/sendemail-validate.sample
.git/hooks/update.sample
.git/index
.git/info/exclude
.git/logs/HEAD
.git/logs/refs/heads/main
.git/logs/refs/remotes/origin/main
.git/objects/07/38cef6db65fccabac1619bbcffe641313b2507
.git/objects/11/516d273922a7e7c0cf5297ed232901bc4d3722
.git/objects/11/fb2c9db70668a2ec0fcf87e1ac6eaaaf9557b2
.git/objects/19/fcf308591853bc76c49970b6b9b2864e1afc12
.git/objects/1f/4013dfc8dd598f625a95b463c28a39db173422
.git/objects/24/1666e8820828287944ec35e473048da8b90731
.git/objects/35/657b7200b0aca4e1e242e090fd032019215474
.git/objects/37/c5de7868e32ef0670df784181f47c59612e374
.git/objects/3d/eea1d625defcca680f35b6c23c0fa66d338074
.git/objects/40/327c9b4c944c767bcbed9150f27c2891dfd31a
.git/objects/42/e78b2d6be457d7b516ebc430d68515db6e4b59
.git/objects/45/f2297ffd61d8fb31e48864ad4bd8e8d71dcd3f
.git/objects/53/52ef1182f679565b4f117edbd87194df3a631f
.git/objects/53/eb89f4e956938c5e90f17e85af9001f2fe48ed
.git/objects/57/87c5e2b6750b7a9f287e8c9ea9863802a7e2f3
.git/objects/5a/caf53ccb5f323932a4f6e30d92618c6dbf5e1d
.git/objects/64/c2c3069516db7cb6319ad7ec92737f00ccb9b5
.git/objects/68/78df8c17eb9c86b3704550ff27b16c8f5b8f62
.git/objects/74/53ffa96dfc990396a15cfa0b2763894f82dd45
.git/objects/75/aade07a9312796e577784b9a3e0b2f5788b764
.git/objects/77/a14edf9cfbfac59ad3fa83743fda439c349164
.git/objects/78/fe7452b90e193bd81dfda01bba7cde03e21f69
.git/objects/79/40dc0b359049f2e9caa953b2327475a147cb04
.git/objects/7f/f1d8ff4187db7134985178eb8e0986f60fe597
.git/objects/85/7732fd3e08573f70f74d3b19a4a05baa3aac4c
botsy-0.1.36.dist-info/LICENSE
botsy-0.1.36.dist-info/METADATA
botsy-0.1.36.dist-info/WHEEL
botsy-0.1.36.dist-info/entry_points.txt
botsy-0.1.36.dist-info/RECORD
