Metadata-Version: 2.1
Name: botsy
Version: 0.1.36
Summary: An interactive chat program
Author: John Furr
Author-email: john.furr@gmail.com
Requires-Python: >=3.8.1,<3.12
Classifier: Programming Language :: Python :: 3
Classifier: Programming Language :: Python :: 3.9
Classifier: Programming Language :: Python :: 3.10
Classifier: Programming Language :: Python :: 3.11
Requires-Dist: boto3 (>=1.26.165,<2.0.0)
Requires-Dist: jprint (>=1.6,<2.0)
Requires-Dist: openai (>=0.27.8,<0.28.0)
Requires-Dist: pydub (>=0.25.1,<0.26.0)
Requires-Dist: pygame (>=2.5.0,<3.0.0)
Requires-Dist: python-dotenv (>=1.0.0,<2.0.0)
Requires-Dist: speechrecognition (>=3.10.0,<4.0.0)
